fixit/__init__.py
fixit/__main__.py
fixit/__version__.py
fixit/api.py
fixit/cli.py
fixit/config.py
fixit/engine.py
fixit/format.py
fixit/ftypes.py
fixit/lsp.py
fixit/py.typed
fixit/rule.py
fixit/testing.py
fixit/util.py
fixit/local/__init__.py
fixit/rules/__init__.py
fixit/rules/avoid_or_in_except.py
fixit/rules/chained_instance_check.py
fixit/rules/cls_in_classmethod.py
fixit/rules/compare_primitives_by_equal.py
fixit/rules/compare_singleton_primitives_by_is.py
fixit/rules/deprecated_abc_import.py
fixit/rules/deprecated_unittest_asserts.py
fixit/rules/no_assert_true_for_comparison.py
fixit/rules/no_inherit_from_object.py
fixit/rules/no_namedtuple.py
fixit/rules/no_redundant_arguments_super.py
fixit/rules/no_redundant_fstring.py
fixit/rules/no_redundant_lambda.py
fixit/rules/no_redundant_list_comprehension.py
fixit/rules/no_static_if_condition.py
fixit/rules/no_string_type_annotation.py
fixit/rules/replace_union_with_optional.py
fixit/rules/rewrite_to_comprehension.py
fixit/rules/rewrite_to_literal.py
fixit/rules/sorted_attributes_rule.py
fixit/rules/use_assert_in.py
fixit/rules/use_assert_is_not_none.py
fixit/rules/use_async_sleep_in_async_def.py
fixit/rules/use_fstring.py
fixit/rules/use_types_from_typing.py
fixit/rules/variadic_callable_syntax.py
fixit/rules/extra/__init__.py
fixit/rules/extra/explicit_frozen_dataclass.py
fixit/rules/extra/use_lint_fixme_comment.py
fixit/tests/__init__.py
fixit/tests/__main__.py
fixit/tests/config.py
fixit/tests/engine.py
fixit/tests/ftypes.py
fixit/tests/rule.py
fixit/tests/smoke.py
fixit/upgrade/__init__.py
fixit/upgrade/deprecated_import.py
fixit/upgrade/deprecated_testcase_keywords.py
fixit/upgrade/remove_rule_suffix.py
fixit-2.2.1.dist-info/METADATA
fixit-2.2.1.dist-info/WHEEL
fixit-2.2.1.dist-info/entry_points.txt
fixit-2.2.1.dist-info/licenses/LICENSE
fixit-2.2.1.dist-info/RECORD
